[
  {
    "name": "Default test - Consultations API",
    "value": "{\n  \"url\": \"https://sandbox.intuned.dev/consultations/list\",\n  \"api_pattern\": \"/rest/v1/consultations\",\n  \"max_pages\": 3\n}",
    "lastUsed": true,
    "id": "e1f2a3b4-c5d6-7890-1234-56789abcdef0"
  },
  {
    "name": "Full scrape - 10 pages",
    "value": "{\n  \"url\": \"https://sandbox.intuned.dev/consultations/list\",\n  \"api_pattern\": \"/rest/v1/consultations\",\n  \"max_pages\": 10\n}",
    "lastUsed": false,
    "id": "f2a3b4c5-d6e7-8901-2345-6789abcdef01"
  },
  {
    "name": "Single page only",
    "value": "{\n  \"url\": \"https://sandbox.intuned.dev/consultations/list\",\n  \"api_pattern\": \"/rest/v1/consultations\",\n  \"max_pages\": 1\n}",
    "lastUsed": false,
    "id": "a3b4c5d6-e7f8-9012-3456-789abcdef012"
  }
]
